setup.cfg
setup.py
pyfem1d/__init__.py
pyfem1d/analysis.py
pyfem1d/helper.py
pyfem1d/load.py
pyfem1d/load_defaults.py
pyfem1d/main.py
pyfem1d/pyfem1d_cmd.py
pyfem1d/umat.py
pyfem1d/umat_defaults.py
pyfem1d.egg-info/PKG-INFO
pyfem1d.egg-info/SOURCES.txt
pyfem1d.egg-info/dependency_links.txt
pyfem1d.egg-info/entry_points.txt
pyfem1d.egg-info/requires.txt
pyfem1d.egg-info/top_level.txt