Metadata-Version: 1.1
Name: pyfem1d
Version: 0.0.2.post1
Summary: 1d finite elements for testing material formulations
Home-page: https://github.com/hos/pyfem1d
Author: H. Onur Solmaz
Author-email: hos@solmaz.co
License: UNKNOWN
Download-URL: https://github.com/hos/pyfem1d/tarball/0.0.2.post1
Keywords: FEM,materials,mechanics
Platform: UNKNOWN
